atk/Docker.py
atk/DockerError.py
atk/__init__.py
atk-0.1.3.8b0.dist-info/LICENSE
atk-0.1.3.8b0.dist-info/METADATA
atk-0.1.3.8b0.dist-info/WHEEL
atk-0.1.3.8b0.dist-info/top_level.txt
atk-0.1.3.8b0.dist-info/RECORD
